.coveragerc
.env
.testr.conf
AUTHORS
ChangeLog
README.rst
config.yml
requirement-conda.txt
requirements.in
requirements.txt
setup.cfg
setup.py
template_test.pytemplate
test-requirements.in
test-requirements.txt
tox.ini
general/__init__.py
general/cli.py
general/cy.py
general/essential.py
general/example.py
general/general.conf
general/gs.py
general/gy.py
general/init_gs.py
general/ly.py
general/monkey_patch.py
general/reflection.py
general/shell_task.py
general/smartlog.py
general/timecount.py
general/unit.py
general/version.py
general.egg-info/PKG-INFO
general.egg-info/SOURCES.txt
general.egg-info/dependency_links.txt
general.egg-info/entry_points.txt
general.egg-info/not-zip-safe
general.egg-info/pbr.json
general.egg-info/requires.txt
general.egg-info/top_level.txt
general/interpreter/__init__.py
general/interpreter/context.py
general/interpreter/loader.py
general/interpreter/runner.py
general/module_settings/task.yaml
general/project_gen/__init__.py
general/project_gen/target/commutils/.coveragerc
general/project_gen/target/commutils/.gitignore
general/project_gen/target/commutils/.testr.conf
general/project_gen/target/commutils/README.md
general/project_gen/target/commutils/requirement-conda.txt
general/project_gen/target/commutils/requirements.txt
general/project_gen/target/commutils/setup.cfg
general/project_gen/target/commutils/setup.py
general/project_gen/target/commutils/test-requirements.txt
general/project_gen/target/commutils/tox.ini
general/project_gen/target/commutils/docs/Makefile
general/project_gen/target/commutils/docs/make.bat
general/project_gen/target/commutils/docs/source/conf.py
general/project_gen/target/commutils/docs/source/index.rst
general/project_gen/template/project/.coveragerc
general/project_gen/template/project/.gitignore
general/project_gen/template/project/.testr.conf
general/project_gen/template/project/README.rst
general/project_gen/template/project/config.py
general/project_gen/template/project/config.yml
general/project_gen/template/project/requirement-conda.txt
general/project_gen/template/project/requirements.txt
general/project_gen/template/project/setup.cfg
general/project_gen/template/project/setup.py
